{
  "name": "serialized_object",
  "properties": {
    "serializedObjectId": {
      "type": "number",
      "required": false,
      "length": null,
      "precision": 10,
      "scale": 0,
      "id": 1,
      "mysql": {
        "columnName": "serialized_object_id",
        "dataType": "int",
        "dataLength": null,
        "dataPrecision": 10,
        "dataScale": 0,
        "nullable": "N"
      },
      "updateOnly": false
    },
    "name": {
      "type": "string",
      "required": true,
      "length": 255,
      "precision": null,
      "scale": null,
      "mysql": {
        "columnName": "name",
        "dataType": "varchar",
        "dataLength": 255,
        "dataPrecision": null,
        "dataScale": null,
        "nullable": "N"
      }
    },
    "description": {
      "type": "string",
      "required": false,
      "length": 5000,
      "precision": null,
      "scale": null,
      "mysql": {
        "columnName": "description",
        "dataType": "varchar",
        "dataLength": 5000,
        "dataPrecision": null,
        "dataScale": null,
        "nullable": "Y"
      }
    },
    "type": {
      "type": "string",
      "required": true,
      "length": 255,
      "precision": null,
      "scale": null,
      "mysql": {
        "columnName": "type",
        "dataType": "varchar",
        "dataLength": 255,
        "dataPrecision": null,
        "dataScale": null,
        "nullable": "N"
      }
    },
    "subtype": {
      "type": "string",
      "required": true,
      "length": 255,
      "precision": null,
      "scale": null,
      "mysql": {
        "columnName": "subtype",
        "dataType": "varchar",
        "dataLength": 255,
        "dataPrecision": null,
        "dataScale": null,
        "nullable": "N"
      }
    },
    "serializationClass": {
      "type": "string",
      "required": true,
      "length": 255,
      "precision": null,
      "scale": null,
      "mysql": {
        "columnName": "serialization_class",
        "dataType": "varchar",
        "dataLength": 255,
        "dataPrecision": null,
        "dataScale": null,
        "nullable": "N"
      }
    },
    "serializedData": {
      "type": "string",
      "required": true,
      "length": 65535,
      "precision": null,
      "scale": null,
      "mysql": {
        "columnName": "serialized_data",
        "dataType": "text",
        "dataLength": 65535,
        "dataPrecision": null,
        "dataScale": null,
        "nullable": "N"
      }
    },
    "dateCreated": {
      "type": "date",
      "required": true,
      "length": null,
      "precision": null,
      "scale": null,
      "mysql": {
        "columnName": "date_created",
        "dataType": "datetime",
        "dataLength": null,
        "dataPrecision": null,
        "dataScale": null,
        "nullable": "N"
      }
    },
    "creator": {
      "type": "number",
      "required": true,
      "length": null,
      "precision": 10,
      "scale": 0,
      "mysql": {
        "columnName": "creator",
        "dataType": "int",
        "dataLength": null,
        "dataPrecision": 10,
        "dataScale": 0,
        "nullable": "N"
      }
    },
    "dateChanged": {
      "type": "date",
      "required": false,
      "length": null,
      "precision": null,
      "scale": null,
      "mysql": {
        "columnName": "date_changed",
        "dataType": "datetime",
        "dataLength": null,
        "dataPrecision": null,
        "dataScale": null,
        "nullable": "Y"
      }
    },
    "changedBy": {
      "type": "number",
      "required": false,
      "length": null,
      "precision": 10,
      "scale": 0,
      "mysql": {
        "columnName": "changed_by",
        "dataType": "int",
        "dataLength": null,
        "dataPrecision": 10,
        "dataScale": 0,
        "nullable": "Y"
      }
    },
    "retired": {
      "type": "number",
      "required": true,
      "length": null,
      "precision": 5,
      "scale": 0,
      "mysql": {
        "columnName": "retired",
        "dataType": "smallint",
        "dataLength": null,
        "dataPrecision": 5,
        "dataScale": 0,
        "nullable": "N"
      }
    },
    "dateRetired": {
      "type": "date",
      "required": false,
      "length": null,
      "precision": null,
      "scale": null,
      "mysql": {
        "columnName": "date_retired",
        "dataType": "datetime",
        "dataLength": null,
        "dataPrecision": null,
        "dataScale": null,
        "nullable": "Y"
      }
    },
    "retiredBy": {
      "type": "number",
      "required": false,
      "length": null,
      "precision": 10,
      "scale": 0,
      "mysql": {
        "columnName": "retired_by",
        "dataType": "int",
        "dataLength": null,
        "dataPrecision": 10,
        "dataScale": 0,
        "nullable": "Y"
      }
    },
    "retireReason": {
      "type": "string",
      "required": false,
      "length": 1000,
      "precision": null,
      "scale": null,
      "mysql": {
        "columnName": "retire_reason",
        "dataType": "varchar",
        "dataLength": 1000,
        "dataPrecision": null,
        "dataScale": null,
        "nullable": "Y"
      }
    },
    "uuid": {
      "type": "string",
      "required": true,
      "length": 38,
      "precision": null,
      "scale": null,
      "mysql": {
        "columnName": "uuid",
        "dataType": "char",
        "dataLength": 38,
        "dataPrecision": null,
        "dataScale": null,
        "nullable": "N"
      }
    }
  },
  "settings": {
    "strict": false,
    "forceId": false,
    "replaceOnPUT": true,
    "idInjection": false,
    "mysql": {
      "schema": "openmrs",
      "table": "serialized_object"
    }
  }
}